slmsuite/__init__.py
slmsuite/hardware/__init__.py
slmsuite/hardware/_pyglet.py
slmsuite/hardware/cameraslms.py
slmsuite/hardware/remote.py
slmsuite/hardware/cameras/__init__.py
slmsuite/hardware/cameras/alliedvision.py
slmsuite/hardware/cameras/basler.py
slmsuite/hardware/cameras/camera.py
slmsuite/hardware/cameras/flir.py
slmsuite/hardware/cameras/imagingsource.py
slmsuite/hardware/cameras/instrumental.py
slmsuite/hardware/cameras/mindvision.py
slmsuite/hardware/cameras/mmcore.py
slmsuite/hardware/cameras/pylablib.py
slmsuite/hardware/cameras/remote.py
slmsuite/hardware/cameras/simulated.py
slmsuite/hardware/cameras/template.py
slmsuite/hardware/cameras/thorlabs.py
slmsuite/hardware/cameras/webcam.py
slmsuite/hardware/cameras/xenics.py
slmsuite/hardware/slms/__init__.py
slmsuite/hardware/slms/_slm_win.py
slmsuite/hardware/slms/hamamatsu.py
slmsuite/hardware/slms/holoeye.py
slmsuite/hardware/slms/meadowlark.py
slmsuite/hardware/slms/remote.py
slmsuite/hardware/slms/santec.py
slmsuite/hardware/slms/screenmirrored.py
slmsuite/hardware/slms/simulated.py
slmsuite/hardware/slms/slm.py
slmsuite/hardware/slms/template.py
slmsuite/hardware/slms/thorlabs.py
slmsuite/holography/__init__.py
slmsuite/holography/algorithms/__init__.py
slmsuite/holography/algorithms/_feedback.py
slmsuite/holography/algorithms/_header.py
slmsuite/holography/algorithms/_hologram.py
slmsuite/holography/algorithms/_multiplane.py
slmsuite/holography/algorithms/_spots.py
slmsuite/holography/algorithms/_stats.py
slmsuite/holography/analysis/__init__.py
slmsuite/holography/analysis/files.py
slmsuite/holography/analysis/fitfunctions.py
slmsuite/holography/toolbox/__init__.py
slmsuite/holography/toolbox/cuda.cu
slmsuite/holography/toolbox/phase.py
slmsuite/misc/__init__.py
slmsuite/misc/files.py
slmsuite/misc/fitfunctions.py
slmsuite/misc/math.py
slmsuite-0.3.0.dist-info/licenses/LICENSE
slmsuite-0.3.0.dist-info/METADATA
slmsuite-0.3.0.dist-info/WHEEL
slmsuite-0.3.0.dist-info/top_level.txt
slmsuite-0.3.0.dist-info/RECORD
