Metadata-Version: 2.4
Name: slmsuite
Version: 0.3.0
Summary: Package for high-performance spatial light modulator (SLM) control and holography.
Author: slmsuite developers
Author-email: qp-slm@mit.edu
Project-URL: Homepage, https://github.com/slmsuite/slmsuite
Project-URL: Documentation, https://slmsuite.readthedocs.io/en/latest/
Classifier: Programming Language :: Python :: 3
Classifier: License :: OSI Approved :: MIT License
Classifier: Operating System :: OS Independent
Requires-Python: >=3.8
License-File: LICENSE
Requires-Dist: numpy
Requires-Dist: scipy
Requires-Dist: opencv-python
Requires-Dist: matplotlib
Requires-Dist: h5py
Requires-Dist: tqdm
Dynamic: author
Dynamic: author-email
Dynamic: license-file
Dynamic: requires-dist
Dynamic: summary
